marble_client/__init__.py
marble_client/client.py
marble_client/constants.py
marble_client/exceptions.py
marble_client/node.py
marble_client/services.py
marble_client/utils.py
marble_client-1.3.0.dist-info/licenses/LICENSE
marble_client-1.3.0.dist-info/METADATA
marble_client-1.3.0.dist-info/WHEEL
marble_client-1.3.0.dist-info/top_level.txt
marble_client-1.3.0.dist-info/RECORD
