Metadata-Version: 2.4
Name: marble_client
Version: 1.3.0
Summary: A python client to access information about the Marble climate infomatics network
Author-email: Deepak Chandan <dchandan@cs.toronto.edu>
License: MIT License
Project-URL: Bug Tracker, https://github.com/DACCS-Climate/marble_client_python/issues
Project-URL: Homepage, https://github.com/DACCS-Climate/marble_client_python
Keywords: climate,climate infomatics,climate data,DACCS,Marble
Classifier: Programming Language :: Python :: 3
Classifier: License :: OSI Approved :: MIT License
Classifier: Operating System :: OS Independent
Requires-Python: >=3.9
License-File: LICENSE
Requires-Dist: platformdirs~=4.2
Requires-Dist: python-dateutil~=2.8
Requires-Dist: requests~=2.31
Provides-Extra: test
Requires-Dist: pytest~=8.2; extra == "test"
Requires-Dist: responses~=0.25; extra == "test"
Requires-Dist: ipywidgets~=8.1; extra == "test"
Provides-Extra: dev
Requires-Dist: bump2version~=1.0; extra == "dev"
Requires-Dist: ruff~=0.9; extra == "dev"
Requires-Dist: pre-commit~=4.1; extra == "dev"
Dynamic: license-file
